Workbook

Sheet How to use
A1: HRMS Portal - QA Test Case Sheet
A2: Scope: HRMS only (auth, employees, org setup, attendance, WFH, leave, comp-off, payroll). LMS/course features are not covered.
A3: Built from the code of rahul52us/hrms-portal-new-backend and rahul52us/hrms-portal-new-frontend (rules, validation messages and existing unit tests).
A5: How to use
A6: 1. Go to the 'Test Cases' sheet. Cells with a yellow header (Status, Actual Result, Tester, Date, Bug ID) are the ones you fill in. Everything else is the test design.
A7: 2. Follow 'Steps' using 'Test Data', then compare with 'Expected Result'. Set Status to Pass / Fail / Blocked / N/A.
A8: 3. On Fail, write what actually happened in 'Actual Result' and add the bug id.
A9: 4. The 'Summary' sheet updates automatically from the Status column.
A10: 5. Numbers marked '(per fixture)' or based on a policy value (e.g. WFH limit 2/week) need the same configuration in your test environment.
A12: Legend
A13: Type: Positive = happy path | Negative = should be refused | Validation = field rules | Boundary = limit values | Edge = unusual situation | Permission = role/access | UI = screen behaviour
A14: Priority: P0 = release blocker | P1 = high | P2 = medium | P3 = low
... A17: Example of a filled row
A18: TC ID | B18: Scenario | C18: Status | D18: Actual Result | E18: Tester | F18: Date | G18: Bug ID
A19: AUTH-003 | B19: Wrong password | C19: Fail | D19: Login succeeded with a wrong password | E19: Priya | F19: 2026-10-22 | G19: BUG-101
A21: Status note: rows marked Pass by 'Claude (auto)' were verified by running the backend logic only (calculators, validators, rules). Screens, API calls and database flows could not be run in that environment and are still 'Not Run'.

Sheet Summary
A1: Execution summary
A3: Module | B3: Total | C3: Pass | D3: Fail | E3: Blocked | F3: N/A | G3: Not Run | H3: % Executed | I3: P0 cases | J3: P0 not passed
A4: Authentication | B4: =COUNTIF('Test Cases'!$B$2:$B$287,$A4) -> 40 | C4: =COUNTIFS('Test Cases'!$B$2:$B$287,$A4,'Test Cases'!$M$2:$M$287,"Pass") -> 3 | D4: =COUNTIFS('Test Cases'!$B$2:$B$287,$A4,'Test Cases'!$M$2:$M$287,"Fail") -> 0 | E4: =COUNTIFS('Test Cases'!$B$2:$B$287,$A4,'Test Cases'!$M$2:$M$287,"Blocked") -> 0 | F4: =COUNTIFS('Test Cases'!$B$2:$B$287,$A4,'Test Cases'!$M$2:$M$287,"N/A") -> 0 | G4: =COUNTIFS('Test Cases'!$B$2:$B$287,$A4,'Test Cases'!$M$2:$M$287,"Not Run") -> 37 | H4: =IF(B4=0,0,(B4-G4)/B4) -> 0.075 | I4: =COUNTIFS('Test Cases'!$B$2:$B$287,$A4,'Test Cases'!$F$2:$F$287,"P0") -> 10 | J4: =I4-COUNTIFS('Test Cases'!$B$2:$B$287,$A4,'Test Cases'!$F$2:$F$287,"P0",'Test Cases'!$M$2:$M$287,"Pass") -> 7
A5: Employees & Users | B5: =COUNTIF('Test Cases'!$B$2:$B$287,$A5) -> 30 | C5: =COUNTIFS('Test Cases'!$B$2:$B$287,$A5,'Test Cases'!$M$2:$M$287,"Pass") -> 8 | D5: =COUNTIFS('Test Cases'!$B$2:$B$287,$A5,'Test Cases'!$M$2:$M$287,"Fail") -> 0 | E5: =COUNTIFS('Test Cases'!$B$2:$B$287,$A5,'Test Cases'!$M$2:$M$287,"Blocked") -> 0 | F5: =COUNTIFS('Test Cases'!$B$2:$B$287,$A5,'Test Cases'!$M$2:$M$287,"N/A") -> 0 | G5: =COUNTIFS('Test Cases'!$B$2:$B$287,$A5,'Test Cases'!$M$2:$M$287,"Not Run") -> 22 | H5: =IF(B5=0,0,(B5-G5)/B5) -> 0.26666667 | I5: =COUNTIFS('Test Cases'!$B$2:$B$287,$A5,'Test Cases'!$F$2:$F$287,"P0") -> 5 | J5: =I5-COUNTIFS('Test Cases'!$B$2:$B$287,$A5,'Test Cases'!$F$2:$F$287,"P0",'Test Cases'!$M$2:$M$287,"Pass") -> 5
A6: Employee Profile | B6: =COUNTIF('Test Cases'!$B$2:$B$287,$A6) -> 10 | C6: =COUNTIFS('Test Cases'!$B$2:$B$287,$A6,'Test Cases'!$M$2:$M$287,"Pass") -> 0 | D6: =COUNTIFS('Test Cases'!$B$2:$B$287,$A6,'Test Cases'!$M$2:$M$287,"Fail") -> 0 | E6: =COUNTIFS('Test Cases'!$B$2:$B$287,$A6,'Test Cases'!$M$2:$M$287,"Blocked") -> 0 | F6: =COUNTIFS('Test Cases'!$B$2:$B$287,$A6,'Test Cases'!$M$2:$M$287,"N/A") -> 0 | G6: =COUNTIFS('Test Cases'!$B$2:$B$287,$A6,'Test Cases'!$M$2:$M$287,"Not Run") -> 10 | H6: =IF(B6=0,0,(B6-G6)/B6) -> 0 | I6: =COUNTIFS('Test Cases'!$B$2:$B$287,$A6,'Test Cases'!$F$2:$F$287,"P0") -> 1 | J6: =I6-COUNTIFS('Test Cases'!$B$2:$B$287,$A6,'Test Cases'!$F$2:$F$287,"P0",'Test Cases'!$M$2:$M$287,"Pass") -> 1
A7: Roles & Permissions | B7: =COUNTIF('Test Cases'!$B$2:$B$287,$A7) -> 7 | C7: =COUNTIFS('Test Cases'!$B$2:$B$287,$A7,'Test Cases'!$M$2:$M$287,"Pass") -> 4 | D7: =COUNTIFS('Test Cases'!$B$2:$B$287,$A7,'Test Cases'!$M$2:$M$287,"Fail") -> 0 | E7: =COUNTIFS('Test Cases'!$B$2:$B$287,$A7,'Test Cases'!$M$2:$M$287,"Blocked") -> 0 | F7: =COUNTIFS('Test Cases'!$B$2:$B$287,$A7,'Test Cases'!$M$2:$M$287,"N/A") -> 0 | G7: =COUNTIFS('Test Cases'!$B$2:$B$287,$A7,'Test Cases'!$M$2:$M$287,"Not Run") -> 3 | H7: =IF(B7=0,0,(B7-G7)/B7) -> 0.57142857 | I7: =COUNTIFS('Test Cases'!$B$2:$B$287,$A7,'Test Cases'!$F$2:$F$287,"P0") -> 2 | J7: =I7-COUNTIFS('Test Cases'!$B$2:$B$287,$A7,'Test Cases'!$F$2:$F$287,"P0",'Test Cases'!$M$2:$M$287,"Pass") -> 2
A8: Organization Setup | B8: =COUNTIF('Test Cases'!$B$2:$B$287,$A8) -> 20 | C8: =COUNTIFS('Test Cases'!$B$2:$B$287,$A8,'Test Cases'!$M$2:$M$287,"Pass") -> 0 | D8: =COUNTIFS('Test Cases'!$B$2:$B$287,$A8,'Test Cases'!$M$2:$M$287,"Fail") -> 0 | E8: =COUNTIFS('Test Cases'!$B$2:$B$287,$A8,'Test Cases'!$M$2:$M$287,"Blocked") -> 0 | F8: =COUNTIFS('Test Cases'!$B$2:$B$287,$A8,'Test Cases'!$M$2:$M$287,"N/A") -> 0 | G8: =COUNTIFS('Test Cases'!$B$2:$B$287,$A8,'Test Cases'!$M$2:$M$287,"Not Run") -> 20 | H8: =IF(B8=0,0,(B8-G8)/B8) -> 0 | I8: =COUNTIFS('Test Cases'!$B$2:$B$287,$A8,'Test Cases'!$F$2:$F$287,"P0") -> 2 | J8: =I8-COUNTIFS('Test Cases'!$B$2:$B$287,$A8,'Test Cases'!$F$2:$F$287,"P0",'Test Cases'!$M$2:$M$287,"Pass") -> 2
A9: Attendance | B9: =COUNTIF('Test Cases'!$B$2:$B$287,$A9) -> 40 | C9: =COUNTIFS('Test Cases'!$B$2:$B$287,$A9,'Test Cases'!$M$2:$M$287,"Pass") -> 14 | D9: =COUNTIFS('Test Cases'!$B$2:$B$287,$A9,'Test Cases'!$M$2:$M$287,"Fail") -> 0 | E9: =COUNTIFS('Test Cases'!$B$2:$B$287,$A9,'Test Cases'!$M$2:$M$287,"Blocked") -> 0 | F9: =COUNTIFS('Test Cases'!$B$2:$B$287,$A9,'Test Cases'!$M$2:$M$287,"N/A") -> 0 | G9: =COUNTIFS('Test Cases'!$B$2:$B$287,$A9,'Test Cases'!$M$2:$M$287,"Not Run") -> 26 | H9: =IF(B9=0,0,(B9-G9)/B9) -> 0.35 | I9: =COUNTIFS('Test Cases'!$B$2:$B$287,$A9,'Test Cases'!$F$2:$F$287,"P0") -> 8 | J9: =I9-COUNTIFS('Test Cases'!$B$2:$B$287,$A9,'Test Cases'!$F$2:$F$287,"P0",'Test Cases'!$M$2:$M$287,"Pass") -> 4
A10: Remote Work (WFH) | B10: =COUNTIF('Test Cases'!$B$2:$B$287,$A10) -> 12 | C10: =COUNTIFS('Test Cases'!$B$2:$B$287,$A10,'Test Cases'!$M$2:$M$287,"Pass") -> 4 | D10: =COUNTIFS('Test Cases'!$B$2:$B$287,$A10,'Test Cases'!$M$2:$M$287,"Fail") -> 0 | E10: =COUNTIFS('Test Cases'!$B$2:$B$287,$A10,'Test Cases'!$M$2:$M$287,"Blocked") -> 0 | F10: =COUNTIFS('Test Cases'!$B$2:$B$287,$A10,'Test Cases'!$M$2:$M$287,"N/A") -> 0 | G10: =COUNTIFS('Test Cases'!$B$2:$B$287,$A10,'Test Cases'!$M$2:$M$287,"Not Run") -> 8 | H10: =IF(B10=0,0,(B10-G10)/B10) -> 0.33333333 | I10: =COUNTIFS('Test Cases'!$B$2:$B$287,$A10,'Test Cases'!$F$2:$F$287,"P0") -> 2 | J10: =I10-COUNTIFS('Test Cases'!$B$2:$B$287,$A10,'Test Cases'!$F$2:$F$287,"P0",'Test Cases'!$M$2:$M$287,"Pass") -> 2
A11: Calendar & Workforce Policy | B11: =COUNTIF('Test Cases'!$B$2:$B$287,$A11) -> 8 | C11: =COUNTIFS('Test Cases'!$B$2:$B$287,$A11,'Test Cases'!$M$2:$M$287,"Pass") -> 0 | D11: =COUNTIFS('Test Cases'!$B$2:$B$287,$A11,'Test Cases'!$M$2:$M$287,"Fail") -> 0 | E11: =COUNTIFS('Test Cases'!$B$2:$B$287,$A11,'Test Cases'!$M$2:$M$287,"Blocked") -> 0 | F11: =COUNTIFS('Test Cases'!$B$2:$B$287,$A11,'Test Cases'!$M$2:$M$287,"N/A") -> 0 | G11: =COUNTIFS('Test Cases'!$B$2:$B$287,$A11,'Test Cases'!$M$2:$M$287,"Not Run") -> 8 | H11: =IF(B11=0,0,(B11-G11)/B11) -> 0 | I11: =COUNTIFS('Test Cases'!$B$2:$B$287,$A11,'Test Cases'!$F$2:$F$287,"P0") -> 0 | J11: =I11-COUNTIFS('Test Cases'!$B$2:$B$287,$A11,'Test Cases'!$F$2:$F$287,"P0",'Test Cases'!$M$2:$M$287,"Pass") -> 0
A12: Leave | B12: =COUNTIF('Test Cases'!$B$2:$B$287,$A12) -> 40 | C12: =COUNTIFS('Test Cases'!$B$2:$B$287,$A12,'Test Cases'!$M$2:$M$287,"Pass") -> 15 | D12: =COUNTIFS('Test Cases'!$B$2:$B$287,$A12,'Test Cases'!$M$2:$M$287,"Fail") -> 0 | E12: =COUNTIFS('Test Cases'!$B$2:$B$287,$A12,'Test Cases'!$M$2:$M$287,"Blocked") -> 0 | F12: =COUNTIFS('Test Cases'!$B$2:$B$287,$A12,'Test Cases'!$M$2:$M$287,"N/A") -> 0 | G12: =COUNTIFS('Test Cases'!$B$2:$B$287,$A12,'Test Cases'!$M$2:$M$287,"Not Run") -> 25 | H12: =IF(B12=0,0,(B12-G12)/B12) -> 0.375 | I12: =COUNTIFS('Test Cases'!$B$2:$B$287,$A12,'Test Cases'!$F$2:$F$287,"P0") -> 8 | J12: =I12-COUNTIFS('Test Cases'!$B$2:$B$287,$A12,'Test Cases'!$F$2:$F$287,"P0",'Test Cases'!$M$2:$M$287,"Pass") -> 7
A13: Comp-Off | B13: =COUNTIF('Test Cases'!$B$2:$B$287,$A13) -> 11 | C13: =COUNTIFS('Test Cases'!$B$2:$B$287,$A13,'Test Cases'!$M$2:$M$287,"Pass") -> 9 | D13: =COUNTIFS('Test Cases'!$B$2:$B$287,$A13,'Test Cases'!$M$2:$M$287,"Fail") -> 0 | E13: =COUNTIFS('Test Cases'!$B$2:$B$287,$A13,'Test Cases'!$M$2:$M$287,"Blocked") -> 0 | F13: =COUNTIFS('Test Cases'!$B$2:$B$287,$A13,'Test Cases'!$M$2:$M$287,"N/A") -> 0 | G13: =COUNTIFS('Test Cases'!$B$2:$B$287,$A13,'Test Cases'!$M$2:$M$287,"Not Run") -> 2 | H13: =IF(B13=0,0,(B13-G13)/B13) -> 0.81818182 | I13: =COUNTIFS('Test Cases'!$B$2:$B$287,$A13,'Test Cases'!$F$2:$F$287,"P0") -> 1 | J13: =I13-COUNTIFS('Test Cases'!$B$2:$B$287,$A13,'Test Cases'!$F$2:$F$287,"P0",'Test Cases'!$M$2:$M$287,"Pass") -> 0
A14: Payroll - Setup | B14: =COUNTIF('Test Cases'!$B$2:$B$287,$A14) -> 16 | C14: =COUNTIFS('Test Cases'!$B$2:$B$287,$A14,'Test Cases'!$M$2:$M$287,"Pass") -> 5 | D14: =COUNTIFS('Test Cases'!$B$2:$B$287,$A14,'Test Cases'!$M$2:$M$287,"Fail") -> 0 | E14: =COUNTIFS('Test Cases'!$B$2:$B$287,$A14,'Test Cases'!$M$2:$M$287,"Blocked") -> 0 | F14: =COUNTIFS('Test Cases'!$B$2:$B$287,$A14,'Test Cases'!$M$2:$M$287,"N/A") -> 0 | G14: =COUNTIFS('Test Cases'!$B$2:$B$287,$A14,'Test Cases'!$M$2:$M$287,"Not Run") -> 11 | H14: =IF(B14=0,0,(B14-G14)/B14) -> 0.3125 | I14: =COUNTIFS('Test Cases'!$B$2:$B$287,$A14,'Test Cases'!$F$2:$F$287,"P0") -> 4 | J14: =I14-COUNTIFS('Test Cases'!$B$2:$B$287,$A14,'Test Cases'!$F$2:$F$287,"P0",'Test Cases'!$M$2:$M$287,"Pass") -> 3
A15: Payroll - Calculation | B15: =COUNTIF('Test Cases'!$B$2:$B$287,$A15) -> 22 | C15: =COUNTIFS('Test Cases'!$B$2:$B$287,$A15,'Test Cases'!$M$2:$M$287,"Pass") -> 14 | D15: =COUNTIFS('Test Cases'!$B$2:$B$287,$A15,'Test Cases'!$M$2:$M$287,"Fail") -> 0 | E15: =COUNTIFS('Test Cases'!$B$2:$B$287,$A15,'Test Cases'!$M$2:$M$287,"Blocked") -> 0 | F15: =COUNTIFS('Test Cases'!$B$2:$B$287,$A15,'Test Cases'!$M$2:$M$287,"N/A") -> 0 | G15: =COUNTIFS('Test Cases'!$B$2:$B$287,$A15,'Test Cases'!$M$2:$M$287,"Not Run") -> 8 | H15: =IF(B15=0,0,(B15-G15)/B15) -> 0.63636364 | I15: =COUNTIFS('Test Cases'!$B$2:$B$287,$A15,'Test Cases'!$F$2:$F$287,"P0") -> 2 | J15: =I15-COUNTIFS('Test Cases'!$B$2:$B$287,$A15,'Test Cases'!$F$2:$F$287,"P0",'Test Cases'!$M$2:$M$287,"Pass") -> 1
... A17: Payroll - Payslips & Reports | B17: =COUNTIF('Test Cases'!$B$2:$B$287,$A17) -> 10 | C17: =COUNTIFS('Test Cases'!$B$2:$B$287,$A17,'Test Cases'!$M$2:$M$287,"Pass") -> 1 | D17: =COUNTIFS('Test Cases'!$B$2:$B$287,$A17,'Test Cases'!$M$2:$M$287,"Fail") -> 0 | E17: =COUNTIFS('Test Cases'!$B$2:$B$287,$A17,'Test Cases'!$M$2:$M$287,"Blocked") -> 0 | F17: =COUNTIFS('Test Cases'!$B$2:$B$287,$A17,'Test Cases'!$M$2:$M$287,"N/A") -> 0 | G17: =COUNTIFS('Test Cases'!$B$2:$B$287,$A17,'Test Cases'!$M$2:$M$287,"Not Run") -> 9 | H17: =IF(B17=0,0,(B17-G17)/B17) -> 0.1 | I17: =COUNTIFS('Test Cases'!$B$2:$B$287,$A17,'Test Cases'!$F$2:$F$287,"P0") -> 3 | J17: =I17-COUNTIFS('Test Cases'!$B$2:$B$287,$A17,'Test Cases'!$F$2:$F$287,"P0",'Test Cases'!$M$2:$M$287,"Pass") -> 3
A18: Total | B18: =SUM(B4:B17) -> 286 | C18: =SUM(C4:C17) -> 77 | D18: =SUM(D4:D17) -> 0 | E18: =SUM(E4:E17) -> 0 | F18: =SUM(F4:F17) -> 0 | G18: =SUM(G4:G17) -> 209 | H18: =IF(B18=0,0,(B18-G18)/B18) -> 0.26923077 | I18: =SUM(I4:I17) -> 57 | J18: =SUM(J4:J17) -> 46
A20: Counts update from the Status column of 'Test Cases'. Priority: P0 release blocker.

Sheet Test Cases
A1: TC ID | B1: Module | C1: Sub-module | D1: Scenario | E1: Type | F1: Priority | G1: Role | H1: Preconditions | I1: Steps | J1: Test Data | K1: Expected Result | L1: Source | M1: Status | N1: Actual Result | O1: Tester | P1: Date | Q1: Bug ID
A2: AUTH-001 | B2: Authentication | C2: Login | D2: Login with valid email and password | E2: Positive | F2: P0 | G2: Employee | H2: Active user exists (password set, enabled) | I2: 1. Open /login 2. Enter email 3. Enter password 4. Click Sign In | J2: admin@company.com / Test@1234 | K2: User is logged in and lands on the dashboard; token/session is created. | L2: backend src/services/auth/utils/validation.ts | M2: Not Run
A3: AUTH-002 | B3: Authentication | C3: Login | D3: Email is trimmed and lower-cased before login | E3: Positive | F3: P2 | G3: Employee | H3: Active user exists | I3: 1. Open /login 2. Enter email with spaces and capitals 3. Enter correct password 4. Sign In | J3: ' Admin@Company.COM ' / Test@1234 | K3: Login succeeds; username is treated as admin@company.com. | L3: backend src/services/auth/utils/validation.ts | M3: Not Run
A4: AUTH-003 | B4: Authentication | C4: Login | D4: Wrong password | E4: Negative | F4: P0 | G4: Anonymous | H4: Active user exists | I4: 1. Open /login 2. Enter valid email and wrong password 3. Sign In | J4: admin@company.com / Wrong@1234 | K4: Login rejected with an invalid-credentials error; no session created. | L4: backend src/services/auth/auth.service.ts | M4: Not Run
A5: AUTH-004 | B5: Authentication | C5: Login | D5: Unregistered email | E5: Negative | F5: P1 | G5: Anonymous | H5: Email not in system | I5: 1. Open /login 2. Enter unknown email and any password 3. Sign In | J5: nobody@nowhere.com / Test@1234 | K5: Login rejected; message does not reveal whether the email exists. | L5: backend src/services/auth/auth.service.ts | M5: Not Run
A6: AUTH-005 | B6: Authentication | C6: Login | D6: Empty email | E6: Validation | F6: P1 | G6: Anonymous | H6: - | I6: 1. Open /login 2. Leave email empty 3. Enter password 4. Sign In | J6: email='' / Test@1234 | K6: Error 'Username is required'; request not accepted. | L6: backend src/services/auth/utils/validation.ts | M6: Not Run
A7: AUTH-006 | B7: Authentication | C7: Login | D7: Empty password | E7: Validation | F7: P1 | G7: Anonymous | H7: - | I7: 1. Open /login 2. Enter email 3. Leave password empty 4. Sign In | J7: admin@company.com / '' | K7: Error 'Password is required'. | L7: backend src/services/auth/utils/validation.ts | M7: Not Run
A8: AUTH-007 | B8: Authentication | C8: Login | D8: Username that is not an email | E8: Validation | F8: P1 | G8: Anonymous | H8: - | I8: 1. Open /login 2. Enter text without @ 3. Enter password 4. Sign In | J8: adminuser / Test@1234 | K8: Error 'Username must be a valid email address'. | L8: backend src/services/auth/utils/validation.ts | M8: Not Run
A9: AUTH-008 | B9: Authentication | C9: Login | D9: Password shorter than 8 characters | E9: Validation | F9: P2 | G9: Anonymous | H9: - | I9: 1. Open /login 2. Enter valid email 3. Enter 7-char password 4. Sign In | J9: admin@company.com / Ab1cdef | K9: Request rejected by validation (minimum 8 characters). | L9: backend src/services/auth/utils/validation.ts | M9: Not Run
A10: AUTH-009 | B10: Authentication | C10: Login | D10: Password longer than 128 characters | E10: Edge | F10: P3 | G10: Anonymous | H10: - | I10: 1. Open /login 2. Enter valid email 3. Paste a 129-character password 4. Sign In | J10: 129 x 'A1b' | K10: Request rejected by validation (maximum 128 characters). | L10: backend src/services/auth/utils/validation.ts | M10: Not Run
A11: AUTH-010 | B11: Authentication | C11: Login | D11: Disabled (inactive) user cannot log in | E11: Negative | F11: P0 | G11: Employee | H11: User exists with password but is disabled by admin | I11: 1. Open /login 2. Enter the disabled user's credentials 3. Sign In | J11: disabled.user@company.com / Test@1234 | K11: Login is blocked; user account status is INACTIVE so canUserLogin is false. | L11: backend src/services/auth/utils/userAccountStatus.ts | M11: Pass | N11: Executed probe: Behaved as expected. Logic checked by running the backend code; UI / API / database flow NOT tested. | O11: Claude (auto) | P11: 2026-10-21
A12: AUTH-011 | B12: Authentication | C12: Login | D12: Invited user who has not set a password cannot log in | E12: Negative | F12: P0 | G12: Employee | H12: User created by admin; password not yet set (status PENDING) | I12: 1. Open /login 2. Enter the invited user's email and any password 3. Sign In | J12: new.hire@company.com / Test@1234 | K12: Login is blocked; account is PENDING until a password is set via invite link. | L12: backend src/services/auth/utils/userAccountStatus.ts | M12: Pass | N12: Executed probe: Behaved as expected. Logic checked by running the backend code; UI / API / database flow NOT tested. | O12: Claude (auto) | P12: 2026-10-21
A13: AUTH-012 | B13: Authentication | C13: Login | D13: Deleted user cannot log in | E13: Negative | F13: P0 | G13: Employee | H13: User is soft-deleted (deletedAt set) | I13: 1. Open /login 2. Enter the deleted user's credentials 3. Sign In | J13: deleted.user@company.com / Test@1234 | K13: Login is blocked; DELETED status wins over every other state. | L13: backend src/services/auth/utils/userAccountStatus.ts | M13: Pass | N13: Executed probe: Behaved as expected. Logic checked by running the backend code; UI / API / database flow NOT tested. | O13: Claude (auto) | P13: 2026-10-21
A14: AUTH-013 | B14: Authentication | C14: Login | D14: Login blocked when the user's company is inactive | E14: Negative | F14: P1 | G14: Employee | H14: Company is deactivated by Super Admin | I14: 1. Deactivate the company 2. Login as an employee of that company | J14: employee@inactive-co.com / Test@1234 | K14: Action blocked with message '<Company name> is inactive.' (or 'This company is inactive.'). | L14: backend src/services/company/utils/activityGuards.ts | M14: Not Run
A15: AUTH-014 | B15: Authentication | C15: Login | D15: Show/hide password toggle | E15: UI | F15: P3 | G15: Anonymous | H15: - | I15: 1. Open /login 2. Type a password 3. Click the eye icon | J15: any | K15: Password toggles between masked and visible text. | L15: frontend app/(authentication)/login/page.tsx | M15: Not Run
A16: AUTH-015 | B16: Authentication | C16: Login | D16: Protected page without a session redirects to login | E16: Permission | F16: P0 | G16: Anonymous | H16: Not logged in | I16: 1. Open /dashboard directly in a new browser profile | J16: - | K16: User is redirected to /login; no dashboard data shown. | L16: frontend app/dashboard | M16: Not Run
A17: AUTH-016 | B17: Authentication | C17: Session | D17: Logout clears session | E17: Positive | F17: P1 | G17: Employee | H17: Logged in | I17: 1. Click profile menu 2. Click Logout 3. Press browser Back | J17: - | K17: User returns to login; Back button does not reopen protected pages. | L17: frontend app/dashboard | M17: Not Run
A18: AUTH-017 | B18: Authentication | C18: Session | D18: Expired/invalid token is rejected by API | E18: Negative | F18: P0 | G18: Employee | H18: Logged in | I18: 1. Tamper with or expire the stored token 2. Refresh /dashboard | J18: token='abc.def.ghi' | K18: API returns unauthorized; user is sent to login. | L18: backend src/modules/config/authenticate.ts | M18: Not Run
A19: AUTH-018 | B19: Authentication | C19: Forgot Password | D19: Request reset link with registered email | E19: Positive | F19: P1 | G19: Anonymous | H19: Active user exists | I19: 1. Open /forgot-password 2. Enter registered email 3. Submit | J19: admin@company.com | K19: Success message shown; a reset email with a secure link is sent. | L19: backend src/services/auth/utils/validation.ts | M19: Not Run
A20: AUTH-019 | B20: Authentication | C20: Forgot Password | D20: Request reset with invalid email format | E20: Validation | F20: P2 | G20: Anonymous | H20: - | I20: 1. Open /forgot-password 2. Enter 'abc' 3. Submit | J20: abc | K20: Error 'Username should be a valid email address'. | L20: backend src/services/auth/utils/validation.ts | M20: Not Run
A21: AUTH-020 | B21: Authentication | C21: Forgot Password | D21: Request reset with empty email | E21: Validation | F21: P2 | G21: Anonymous | H21: - | I21: 1. Open /forgot-password 2. Leave empty 3. Submit | J21: '' | K21: Error 'Username is required'. | L21: backend src/services/auth/utils/validation.ts | M21: Not Run
A22: AUTH-021 | B22: Authentication | C22: Reset Password | D22: Reset password with valid token and strong password | E22: Positive | F22: P0 | G22: Anonymous | H22: Valid reset link received by email | I22: 1. Open the reset link 2. Enter a new strong password 3. Submit 4. Login with the new password | J22: NewPass@123 | K22: Password changes; old password stops working; login works with the new one. | L22: backend src/services/auth/utils/validation.ts | M22: Not Run
A23: AUTH-022 | B23: Authentication | C23: Reset Password | D23: Reset with expired/invalid token | E23: Negative | F23: P0 | G23: Anonymous | H23: Expired or random token | I23: 1. Open /reset-password/<bad-token> 2. Enter strong password 3. Submit | J23: token=invalid | K23: Reset rejected with an invalid/expired token error. | L23: backend src/services/auth/auth.service.ts | M23: Not Run
A24: AUTH-023 | B24: Authentication | C24: Reset Password | D24: Reset link cannot be reused | E24: Negative | F24: P1 | G24: Anonymous | H24: Reset already completed once | I24: 1. Use the same link again 2. Submit a new password | J24: - | K24: Second attempt is rejected. | L24: backend src/services/auth/auth.service.ts | M24: Not Run
A25: AUTH-024 | B25: Authentication | C25: Password Rules | D25: Weak password rejected (7 characters) | E25: Boundary | F25: P1 | G25: Anonymous | H25: Valid reset token | I25: 1. Open the reset page 2. Enter 'Pass123' 3. Submit | J25: Pass123 | K25: Password must contain at least 8 characters, including one uppercase letter, one lowercase letter, and one digit. | L25: backend src/services/auth/utils/validation.ts | M25: Not Run
... A48: EMP-007 | B48: Employees & Users | C48: Create Employee | D48: Employee role cannot open user management | E48: Permission | F48: P0 | G48: Employee | H48: Logged in as Employee | I48: 1. Open /dashboard/users directly | J48: - | K48: Access denied / redirected; no user list returned by API. | L48: frontend app/dashboard/users | M48: Not Run
A49: EMP-008 | B49: Employees & Users | C49: Employee Code | D49: Company code is normalized to upper case | E49: Positive | F49: P2 | G49: Company Admin | H49: - | I49: 1. Set company code ' acme ' 2. Save | J49: ' acme ' | K49: Saved as ACME. | L49: backend src/services/employeeCode/employeeCode.utils.ts | M49: Pass | N49: Executed probe: Behaved as expected. Logic checked by running the backend code; UI / API / database flow NOT tested. | O49: Claude (auto) | P49: 2026-10-21
A50: EMP-009 | B50: Employees & Users | C50: Employee Code | D50: Company code length 2 to 20 | E50: Boundary | F50: P2 | G50: Company Admin | H50: - | I50: 1. Try 'A' 2. 'AB' 3. 20 chars 4. 21 chars | J50: A / AB / 20 / 21 chars | K50: 'A' and 21 chars rejected; 'AB' and 20 chars accepted. | L50: backend src/services/employeeCode/employeeCode.utils.ts | M50: Pass | N50: Executed probe: Behaved as expected. Logic checked by running the backend code; UI / API / database flow NOT tested. | O50: Claude (auto) | P50: 2026-10-21
A51: EMP-010 | B51: Employees & Users | C51: Employee Code | D51: Company code allows only letters, digits and single hyphens | E51: Validation | F51: P2 | G51: Company Admin | H51: - | I51: 1. Try 'AC ME' 2. 'ACME-' 3. 'AC--ME' 4. 'AC-ME' | J51: as listed | K51: First three rejected; 'AC-ME' accepted. | L51: backend src/services/employeeCode/employeeCode.utils.ts | M51: Pass | N51: Executed probe: Behaved as expected. Logic checked by running the backend code; UI / API / database flow NOT tested. | O51: Claude (auto) | P51: 2026-10-21
A52: EMP-011 | B52: Employees & Users | C52: Employee Code | D52: Employee number max length 40 | E52: Boundary | F52: P2 | G52: HR | H52: - | I52: 1. Enter 40-char number 2. Enter 41-char number | J52: 40 / 41 chars | K52: 40 accepted; 41 rejected. | L52: backend src/services/employeeCode/employeeCode.utils.ts | M52: Pass | N52: Executed probe: Behaved as expected. Logic checked by running the backend code; UI / API / database flow NOT tested. | O52: Claude (auto) | P52: 2026-10-21
A53: EMP-012 | B53: Employees & Users | C53: Employee Code | D53: Employee ID is built as COMPANY-NUMBER | E53: Positive | F53: P1 | G53: HR | H53: Company code ACME | I53: 1. Create employee with number '0042' | J53: 0042 | K53: Employee ID shown as ACME-0042. | L53: backend src/services/employeeCode/employeeCode.utils.ts | M53: Pass | N53: Executed probe: {"companyCode":"ACME","employeeNumber":"0042","code":"ACME-0042"}. Logic checked by running the backend code; UI / API / database flow NOT tested. | O53: Claude (auto) | P53: 2026-10-21
A54: EMP-013 | B54: Employees & Users | C54: Employee Code | D54: Company prefix typed by user is not duplicated | E54: Edge | F54: P2 | G54: HR | H54: Company code ACME | I54: 1. Enter employee number 'acme-0042' | J54: acme-0042 | K54: ID is ACME-0042 (not ACME-ACME-0042). | L54: backend src/services/employeeCode/employeeCode.utils.ts | M54: Pass | N54: Executed probe: {"companyCode":"ACME","employeeNumber":"0042","code":"ACME-0042"}. Logic checked by running the backend code; UI / API / database flow NOT tested. | O54: Claude (auto) | P54: 2026-10-21
A55: EMP-014 | B55: Employees & Users | C55: Employee Code | D55: Employee number that only looks like the prefix is kept | E55: Edge | F55: P3 | G55: HR | H55: Company code ACME | I55: 1. Enter 'ACMEX-1' | J55: ACMEX-1 | K55: Stored as ACMEX-1 under ACME => ACME-ACMEX-1. | L55: backend src/services/employeeCode/employeeCode.utils.ts | M55: Pass | N55: Executed probe: {"companyCode":"ACME","employeeNumber":"ACMEX-1","code":"ACME-ACMEX-1"}. Logic checked by running the backend code; UI / API / database flow NOT tested. | O55: Claude (auto) | P55: 2026-10-21
A56: EMP-015 | B56: Employees & Users | C56: Employee Code | D56: Duplicate employee number in same company | E56: Negative | F56: P1 | G56: HR | H56: ACME-0042 exists | I56: 1. Create another employee with number 0042 | J56: 0042 | K56: Error 'Employee code already exists (ACME-0042)' naming the owner. | L56: backend src/services/adminUsers/adminUsers.service.ts | M56: Not Run
A57: EMP-016 | B57: Employees & Users | C57: Bulk Upload | D57: Download bulk upload template | E57: Positive | F57: P2 | G57: HR | H57: - | I57: 1. Users > Bulk upload 2. Click Download template | J57: - | K57: Excel template downloads with expected columns. | L57: backend src/routing (GET /bulk/template) | M57: Not Run
A58: EMP-017 | B58: Employees & Users | C58: Bulk Upload | D58: Preview then commit valid file | E58: Positive | F58: P1 | G58: HR | H58: Filled template with 5 valid rows | I58: 1. Upload file 2. Review preview 3. Commit | J58: 5 rows | K58: Preview shows 5 valid rows; commit creates 5 employees. | L58: backend src/routing (POST /bulk, /commit) | M58: Not Run
A59: EMP-018 | B59: Employees & Users | C59: Bulk Upload | D59: File with invalid rows | E59: Negative | F59: P1 | G59: HR | H59: File has 1 duplicate email and 1 missing name | I59: 1. Upload file 2. Review preview | J59: 2 bad rows | K59: Bad rows flagged with reasons; valid rows can still proceed or commit is blocked as designed. | L59: backend src/routing (POST /bulk) | M59: Not Run
A60: EMP-019 | B60: Employees & Users | C60: Bulk Upload | D60: Wrong file type | E60: Negative | F60: P2 | G60: HR | H60: - | I60: 1. Upload a .pdf as bulk file | J60: sample.pdf | K60: Rejected with a clear file-type error. | L60: frontend app/dashboard/users | M60: Not Run
A61: EMP-020 | B61: Employees & Users | C61: Status | D61: Disable an employee | E61: Positive | F61: P0 | G61: HR | H61: Active employee | I61: 1. Open employee 2. Click Disable 3. Confirm | J61: - | K61: Status becomes Inactive; employee can no longer log in. | L61: backend PUT /:id/status | M61: Not Run
A62: EMP-021 | B62: Employees & Users | C62: Status | D62: Re-enable an employee | E62: Positive | F62: P1 | G62: HR | H62: Disabled employee with password | I62: 1. Click Enable | J62: - | K62: Status returns to Active; login works. | L62: backend PUT /:id/status | M62: Not Run
A63: EMP-022 | B63: Employees & Users | C63: Status | D63: Cannot manage user of another company | E63: Permission | F63: P0 | G63: Company Admin | H63: Two companies A and B | I63: 1. As Admin of A, call update on a user of B | J63: userId of B | K63: Rejected; non-superadmin cannot target another company. | L63: backend src/services/company/utils/activityGuards.ts | M63: Not Run
A64: EMP-023 | B64: Employees & Users | C64: Status | D64: Inactive company blocks management actions | E64: Negative | F64: P1 | G64: Company Admin | H64: Company is inactive | I64: 1. Try to add or edit a user | J64: - | K64: Blocked with '<Company name> is inactive.' | L64: backend src/services/company/utils/activityGuards.ts | M64: Not Run
A65: EMP-024 | B65: Employees & Users | C65: Manager | D65: Assign reporting manager | E65: Positive | F65: P1 | G65: HR | H65: Manager exists | I65: 1. Open employee 2. Choose Reporting Manager 3. Save | J65: Manager 'Ravi' | K65: Manager saved; employee appears in manager's team; approvals route to the manager. | L65: backend PUT /:id/manager | M65: Not Run
A66: EMP-025 | B66: Employees & Users | C66: Manager | D66: Employee cannot be their own manager | E66: Negative | F66: P2 | G66: HR | H66: - | I66: 1. Set employee as own manager | J66: same user | K66: Error 'A user cannot be their own reporting manager' (400). | L66: backend PUT /:id/manager | M66: Not Run
A67: EMP-026 | B67: Employees & Users | C67: Access Role | D67: Assign Payroll Executive access role | E67: Positive | F67: P1 | G67: Company Admin | H67: Employee exists | I67: 1. Open employee 2. Set Access Role = Payroll Executive 3. Save | J67: payrollexecutive | K67: Employee gets payroll permissions but organizational role is unchanged. | L67: backend src/services/permissions/permission.utils.test.ts | M67: Pass | N67: Verified by existing test permission.utils.test.ts (ran OK). Logic checked by running the backend code; UI / API / database flow NOT tested. | O67: Claude (auto) | P67: 2026-10-21
A68: EMP-027 | B68: Employees & Users | C68: Search | D68: Search/filter employee list | E68: Positive | F68: P2 | G68: HR | H68: 20+ employees | I68: 1. Type part of a name in search 2. Filter by department | J68: 'Asha' | K68: List shows only matching employees; pagination counts update. | L68: frontend app/dashboard/users | M68: Not Run
A69: EMP-028 | B69: Employees & Users | C69: Create Employee | D69: Duplicate phone number | E69: Negative | F69: P1 | G69: HR | H69: A user with phone 9876543210 exists | I69: 1. Add employee with the same phone 2. Save | J69: 9876543210 | K69: Error 'Phone number already exists (...)'. | L69: backend src/services/adminUsers/adminUsers.service.ts | M69: Not Run
A70: EMP-029 | B70: Employees & Users | C70: Bulk Upload | D70: Duplicate rows are skipped with reason | E70: Negative | F70: P1 | G70: HR | H70: File repeats an existing email, phone and employee code | I70: 1. Upload file 2. Open preview | J70: 3 duplicate rows | K70: Each row shows its error ('Email already exists', 'Phone number already exists', 'Employee code already exists') and a skip reason. | L70: backend src/services/adminUsers/adminUsers.service.ts | M70: Not Run
A71: EMP-030 | B71: Employees & Users | C71: Bulk Upload | D71: Row where user is own manager | E71: Negative | F71: P3 | G71: HR | H71: File row lists the employee as own manager | I71: 1. Upload file | J71: - | K71: Row error 'A user cannot be their own manager'. | L71: backend src/services/adminUsers/adminUsers.service.ts | M71: Not Run
A72: PROF-001 | B72: Employee Profile | C72: Personal details | D72: Employee updates own personal details | E72: Positive | F72: P2 | G72: Employee | H72: Logged in | I72: 1. Open My Profile 2. Edit Personal details 3. Save | J72: DOB, gender, address | K72: Changes saved and shown after refresh. | L72: backend PUT /me/profile/* | M72: Not Run
A73: PROF-002 | B73: Employee Profile | C73: Family details | D73: Employee updates own family details | E73: Positive | F73: P2 | G73: Employee | H73: Logged in | I73: 1. Open My Profile 2. Edit Family details 3. Save | J73: spouse, children | K73: Changes saved and shown after refresh. | L73: backend PUT /me/profile/* | M73: Not Run
A74: PROF-003 | B74: Employee Profile | C74: Skills | D74: Employee updates own skills | E74: Positive | F74: P2 | G74: Employee | H74: Logged in | I74: 1. Open My Profile 2. Edit Skills 3. Save | J74: Excel, SQL | K74: Changes saved and shown after refresh. | L74: backend PUT /me/profile/* | M74: Not Run
A75: PROF-004 | B75: Employee Profile | C75: Statutory details | D75: Employee updates own statutory details | E75: Positive | F75: P2 | G75: Employee | H75: Logged in | I75: 1. Open My Profile 2. Edit Statutory details 3. Save | J75: PAN, UAN, ESIC number | K75: Changes saved and shown after refresh. | L75: backend PUT /me/profile/* | M75: Not Run
A76: PROF-005 | B76: Employee Profile | C76: Profile | D76: Employee cannot edit another employee's profile | E76: Permission | F76: P0 | G76: Employee | H76: - | I76: 1. Call PUT /:id/profile/personal for another user | J76: other userId | K76: Rejected with 403. | L76: backend src/routing/users.routing.ts | M76: Not Run
A77: PROF-006 | B77: Employee Profile | C77: Profile | D77: HR edits an employee's profile | E77: Positive | F77: P1 | G77: HR | H77: edit_users permission | I77: 1. Open employee 2. Edit personal info 3. Save | J77: - | K77: Saved; audit shows HR as editor. | L77: backend PUT /:id/profile/* | M77: Not Run
A78: PROF-007 | B78: Employee Profile | C78: Documents | D78: Upload profile document | E78: Positive | F78: P2 | G78: Employee | H78: - | I78: 1. Profile > Documents 2. Upload PDF 3. Save | J78: aadhaar.pdf | K78: Document listed and downloadable. | L78: frontend app/dashboard/profile/documents | M78: Not Run
A79: PROF-008 | B79: Employee Profile | C79: Documents | D79: Upload unsupported/oversized document | E79: Negative | F79: P2 | G79: Employee | H79: - | I79: 1. Upload .exe or very large file | J79: virus.exe | K79: Rejected with file-type/size error. | L79: frontend app/dashboard/profile/documents | M79: Not Run
... A83: PERM-002 | B83: Roles & Permissions | C83: Role Defaults | D83: HR cannot finalize or reopen payroll by default | E83: Permission | F83: P0 | G83: HR | H83: Default role config | I83: 1. Open payroll run as HR 2. Look for Finalize/Reopen | J83: - | K83: Finalize and Reopen not available; Admin and HR Admin have both. | L83: backend src/services/payroll/payrollFinalization.test.ts; payrollReopen.test.ts | M83: Not Run
A84: PERM-003 | B84: Roles & Permissions | C84: Override | D84: Grant a single permission to one user | E84: Positive | F84: P1 | G84: Company Admin | H84: HR user exists | I84: 1. Open permissions 2. Select user 3. Enable manage_workforce_policies 4. Save | J84: HR user | K84: User gains the permission without a role change. | L84: backend src/services/permissions/permission.utils.test.ts | M84: Pass | N84: Verified by existing test permission.utils.test.ts (ran OK). Logic checked by running the backend code; UI / API / database flow NOT tested. | O84: Claude (auto) | P84: 2026-10-21
A85: PERM-004 | B85: Roles & Permissions | C85: Override | D85: Explicit deny overrides role default | E85: Positive | F85: P1 | G85: Company Admin | H85: - | I85: 1. Disable an inherited permission for a user 2. Save | J85: - | K85: User loses permission even though role grants it. | L85: backend src/services/permissions/permission.utils.test.ts | M85: Pass | N85: Verified by existing test permission.utils.test.ts (ran OK). Logic checked by running the backend code; UI / API / database flow NOT tested. | O85: Claude (auto) | P85: 2026-10-21
A86: PERM-005 | B86: Roles & Permissions | C86: Override | D86: System permissions cannot be delegated to individuals | E86: Negative | F86: P1 | G86: Company Admin | H86: - | I86: 1. Try to grant manage_permissions to one user | J86: manage_permissions | K86: Not allowed; control is disabled or request rejected. | L86: backend src/services/permissions/permission.utils.test.ts | M86: Pass | N86: Verified by existing test permission.utils.test.ts (ran OK). Logic checked by running the backend code; UI / API / database flow NOT tested. | O86: Claude (auto) | P86: 2026-10-21
A87: PERM-006 | B87: Roles & Permissions | C87: Override | D87: Omitted overrides keep inheriting defaults | E87: Edge | F87: P2 | G87: Company Admin | H87: - | I87: 1. Save override for one permission 2. Check other permissions | J87: - | K87: Other permissions still follow the role default. | L87: backend src/services/permissions/permission.utils.test.ts | M87: Pass | N87: Verified by existing test permission.utils.test.ts (ran OK). Logic checked by running the backend code; UI / API / database flow NOT tested. | O87: Claude (auto) | P87: 2026-10-21
A88: PERM-007 | B88: Roles & Permissions | C88: Menu | D88: Sidebar shows only permitted modules | E88: Permission | F88: P0 | G88: Employee | H88: Employee role | I88: 1. Log in and view sidebar | J88: - | K88: Admin modules (Payroll, Permissions, Users) are hidden; My Attendance/My Leave/My Payslips visible. | L88: frontend app/dashboard | M88: Not Run
A89: ORG-001 | B89: Organization Setup | C89: Department | D89: Create department | E89: Positive | F89: P0 | G89: Company Admin | H89: - | I89: 1. Departments > Add 2. Enter name and code 3. Save | J89: Engineering / ENG-01 | K89: Department appears in the list. | L89: frontend app/dashboard/departments/AddDepartment.tsx | M89: Not Run
A90: ORG-002 | B90: Organization Setup | C90: Department | D90: Duplicate team name inside a department | E90: Negative | F90: P2 | G90: Company Admin | H90: Team exists | I90: 1. Add team with the same name | J90: 'Backend' | K90: Error 'Team already exists in this department'. | L90: backend src/services/department | M90: Not Run
A91: ORG-003 | B91: Organization Setup | C91: Department | D91: Team name is required | E91: Validation | F91: P2 | G91: Company Admin | H91: - | I91: 1. Add team with empty name | J91: '' | K91: Error 'Team name is required'. | L91: backend src/services/department | M91: Not Run
A92: ORG-004 | B92: Organization Setup | C92: Department | D92: Delete team that has employees | E92: Negative | F92: P1 | G92: Company Admin | H92: Team has employees | I92: 1. Delete team | J92: - | K92: Blocked: 'This team has assigned employees. Move employees before deleting it.' | L92: backend src/services/department | M92: Not Run
A93: ORG-005 | B93: Organization Setup | C93: Department | D93: Department head must be employee or manager | E93: Negative | F93: P2 | G93: Company Admin | H93: - | I93: 1. Set an admin account as department head | J93: admin user | K93: Error 'Choose an employee or manager, not an admin account'. | L93: backend src/services/department | M93: Not Run
A94: ORG-006 | B94: Organization Setup | C94: Department | D94: Close department with transfer of employees | E94: Positive | F94: P1 | G94: Company Admin | H94: Department with employees; another department exists | I94: 1. Open Department closure drawer 2. Select destination department 3. Enter transfer reason 4. Confirm | J94: reason='Restructure' | K94: Employees move to destination; department archived. | L94: frontend app/dashboard/departments/DepartmentClosureDrawer.tsx | M94: Not Run
A95: ORG-007 | B95: Organization Setup | C95: Department | D95: Closure reason too short | E95: Validation | F95: P2 | G95: Company Admin | H95: - | I95: 1. In closure drawer enter reason 'ab' | J95: ab | K95: Error 'Transfer reason must be at least 3 characters'. | L95: backend src/services/department | M95: Not Run
A96: ORG-008 | B96: Organization Setup | C96: Department | D96: Closure without destination | E96: Negative | F96: P2 | G96: Company Admin | H96: Department has employees | I96: 1. Confirm closure without selecting destination | J96: - | K96: Error 'Select a valid destination department'. | L96: backend src/services/department | M96: Not Run
A97: ORG-009 | B97: Organization Setup | C97: Department | D97: HR cannot manage departments | E97: Permission | F97: P1 | G97: HR | H97: - | I97: 1. Try to add or archive a department | J97: - | K97: Error 'Only superadmin or admin can manage departments'. | L97: backend src/services/department | M97: Not Run
A98: ORG-010 | B98: Organization Setup | C98: Location | D98: Create office location | E98: Positive | F98: P0 | G98: Company Admin | H98: - | I98: 1. Locations > Add 2. Enter name, code, city, state, country, pin, address, lat, lng 3. Save | J98: Delhi Head Office / DEL-HO / 28.6139 / 77.2090 | K98: Location saved and listed. | L98: frontend app/dashboard/locations/LocationModal.tsx | M98: Not Run
A99: ORG-011 | B99: Organization Setup | C99: Location | D99: Required fields | E99: Validation | F99: P1 | G99: Company Admin | H99: - | I99: 1. Save with name, code or city empty | J99: - | K99: Error 'Location name, code, and city are required'. | L99: backend src/services/officeLocation | M99: Not Run
... A110: ATT-002 | B110: Attendance | C110: Punch | D110: Punch out after punch in | E110: Positive | F110: P0 | G110: Employee | H110: Already punched in | I110: 1. Click Punch Out | J110: 18:30 | K110: Session closes; worked minutes computed; day status calculated. | L110: backend src/services/attendance/attendancePunch.test.ts | M110: Not Run
A111: ATT-003 | B111: Attendance | C111: Punch | D111: Punch out without a punch in | E111: Negative | F111: P0 | G111: Employee | H111: No punch-in for the day | I111: 1. Click Punch Out | J111: - | K111: Rejected; punch-out requires a punch-in. | L111: backend src/services/attendance/attendancePunch.test.ts | M111: Pass | N111: Verified by existing test attendancePunch.test.ts (ran OK). Logic checked by running the backend code; UI / API / database flow NOT tested. | O111: Claude (auto) | P111: 2026-10-21
A112: ATT-004 | B112: Attendance | C112: Punch | D112: Second punch-out replaces the first (latest wins) | E112: Edge | F112: P1 | G112: Employee | H112: Punched in 09:30, out 15:00 | I112: 1. Punch out again at 18:00 | J112: 15:00 then 18:00 | K112: Final session is 09:30-18:00; previous punch-out 15:00 kept as history. | L112: backend src/services/attendance/attendancePunch.test.ts | M112: Pass | N112: Verified by existing test attendancePunch.test.ts (ran OK). Logic checked by running the backend code; UI / API / database flow NOT tested. | O112: Claude (auto) | P112: 2026-10-21
A113: ATT-005 | B113: Attendance | C113: Punch | D113: Overnight shift punch-out next morning | E113: Edge | F113: P1 | G113: Employee | H113: Night shift crossing midnight | I113: 1. Punch in 22:00 2. Punch out 06:00 next day | J113: 22:00 -> 06:00 | K113: Punch-out belongs to the previous attendance date; one session recorded. | L113: backend src/services/attendance/attendancePunch.test.ts | M113: Pass | N113: Verified by existing test attendancePunch.test.ts (ran OK). Logic checked by running the backend code; UI / API / database flow NOT tested. | O113: Claude (auto) | P113: 2026-10-21
A114: ATT-006 | B114: Attendance | C114: Punch | D114: Punch inside office geofence | E114: Positive | F114: P1 | G114: Employee | H114: Policy needs geofence; office lat/lng set | I114: 1. Punch in from the office location | J114: Same coordinates as office | K114: Punch accepted; distance 0 m, within geofence. | L114: backend src/services/attendance/attendancePunch.test.ts | M114: Pass | N114: Verified by existing test attendancePunch.test.ts (ran OK). Logic checked by running the backend code; UI / API / database flow NOT tested. | O114: Claude (auto) | P114: 2026-10-21
A115: ATT-007 | B115: Attendance | C115: Punch | D115: Punch outside office geofence | E115: Negative | F115: P1 | G115: Employee | H115: Geofence enforced; office lat/lng set | I115: 1. Punch in from >700 m away | J115: ~700+ m from office | K115: Punch flagged/blocked as outside geofence per policy. | L115: backend src/services/attendance/attendancePunch.test.ts | M115: Pass | N115: Verified by existing test attendancePunch.test.ts (ran OK). Logic checked by running the backend code; UI / API / database flow NOT tested. | O115: Claude (auto) | P115: 2026-10-21
A116: ATT-008 | B116: Attendance | C116: Punch | D116: Punch from an untrusted device | E116: Negative | F116: P1 | G116: Employee | H116: Trusted-device policy is on; device not approved | I116: 1. Punch in from a new browser/device | J116: new device | K116: Punch blocked or sent for approval per punch access policy. | L116: backend src/services/attendance/attendancePunchAccess.test.ts | M116: Not Run
A117: ATT-009 | B117: Attendance | C117: Punch | D117: Approve a trusted device | E117: Positive | F117: P2 | G117: HR | H117: Pending device request | I117: 1. Attendance > Trusted devices 2. Approve the device | J117: - | K117: Employee can punch from the device afterwards. | L117: frontend app/dashboard/attendance/AttendanceTrustedDevicesPanel.tsx | M117: Not Run
A118: ATT-010 | B118: Attendance | C118: Calculation | D118: Full day with overtime | E118: Positive | F118: P0 | G118: Employee | H118: 8-hour shift | I118: 1. Work 9 hours 2. Open the day | J118: worked=540 min | K118: Status 'present', late 0, early exit 0, overtime 60. | L118: backend src/services/attendance/attendanceCalculator.test.ts | M118: Pass | N118: Verified by existing test attendanceCalculator.test.ts (ran OK). Logic checked by running the backend code; UI / API / database flow NOT tested. | O118: Claude (auto) | P118: 2026-10-21
A119: ATT-011 | B119: Attendance | C119: Calculation | D119: Multiple sessions with a break | E119: Positive | F119: P1 | G119: Employee | H119: Two sessions in a day, 60-min gap | I119: 1. Punch in/out twice 2. Open the day | J119: break=60 | K119: Worked 435, break 60, status 'half_day', late 5, early exit 25 (per fixture). | L119: backend src/services/attendance/attendanceCalculator.test.ts | M119: Pass | N119: Verified by existing test attendanceCalculator.test.ts (ran OK). Logic checked by running the backend code; UI / API / database flow NOT tested. | O119: Claude (auto) | P119: 2026-10-21
A120: ATT-012 | B120: Attendance | C120: Calculation | D120: Open session during the day | E120: Edge | F120: P1 | G120: Employee | H120: Punched in, not out, day not closed | I120: 1. Open day view | J120: - | K120: Status 'pending', state 'open', missing punch flagged. | L120: backend src/services/attendance/attendanceCalculator.test.ts | M120: Pass | N120: Verified by existing test attendanceCalculator.test.ts (ran OK). Logic checked by running the backend code; UI / API / database flow NOT tested. | O120: Claude (auto) | P120: 2026-10-21
A121: ATT-013 | B121: Attendance | C121: Calculation | D121: Day closed with no punches | E121: Positive | F121: P0 | G121: Employee | H121: Working day, closed, no punch | I121: 1. Run processor / view day | J121: - | K121: Status 'absent'. | L121: backend src/services/attendance/attendanceCalculator.test.ts | M121: Pass | N121: Verified by existing test attendanceCalculator.test.ts (ran OK). Logic checked by running the backend code; UI / API / database flow NOT tested. | O121: Claude (auto) | P121: 2026-10-21
A122: ATT-014 | B122: Attendance | C122: Calculation | D122: Day closed with only a punch-in | E122: Positive | F122: P0 | G122: Employee | H122: Missing punch-out after close | I122: 1. View day | J122: - | K122: Status 'incomplete' with missing punch flag. | L122: backend src/services/attendance/attendanceCalculator.test.ts | M122: Pass | N122: Verified by existing test attendanceCalculator.test.ts (ran OK). Logic checked by running the backend code; UI / API / database flow NOT tested. | O122: Claude (auto) | P122: 2026-10-21
A123: ATT-015 | B123: Attendance | C123: Calculation | D123: No punch on a weekly off | E123: Positive | F123: P1 | G123: Employee | H123: Sunday = weekly off | I123: 1. View Sunday | J123: - | K123: Status 'weekly_off', not absent. | L123: backend src/services/attendance/attendanceCalculator.test.ts | M123: Pass | N123: Verified by existing test attendanceCalculator.test.ts (ran OK). Logic checked by running the backend code; UI / API / database flow NOT tested. | O123: Claude (auto) | P123: 2026-10-21
A124: ATT-016 | B124: Attendance | C124: Calculation | D124: Work on a holiday | E124: Edge | F124: P1 | G124: Employee | H124: Holiday in calendar | I124: 1. Punch 2 hours on the holiday | J124: 120 min | K124: Status 'present' with 120 worked minutes; may be eligible for comp-off. | L124: backend src/services/attendance/attendanceCalculator.test.ts | M124: Pass | N124: Verified by existing test attendanceCalculator.test.ts (ran OK). Logic checked by running the backend code; UI / API / database flow NOT tested. | O124: Claude (auto) | P124: 2026-10-21
A125: ATT-017 | B125: Attendance | C125: Calculation | D125: Very late arrival cannot be recovered by working after shift | E125: Edge | F125: P1 | G125: Employee | H125: Scheduled window set | I125: 1. Arrive 140 min late 2. Work 8 hours total (after shift end) | J125: late=140, worked=480 | K125: Late 140 and status 'half_day' despite 480 worked. | L125: backend src/services/attendance/attendanceCalculator.test.ts | M125: Pass | N125: Verified by existing test attendanceCalculator.test.ts (ran OK). Logic checked by running the backend code; UI / API / database flow NOT tested. | O125: Claude (auto) | P125: 2026-10-21
A126: ATT-018 | B126: Attendance | C126: Calculation | D126: Shift across midnight is calculated as one day | E126: Edge | F126: P1 | G126: Employee | H126: Night shift | I126: 1. Work a full overnight shift | J126: worked=420 | K126: Status 'present', early exit 0. | L126: backend src/services/attendance/attendanceCalculator.test.ts | M126: Pass | N126: Verified by existing test attendanceCalculator.test.ts (ran OK). Logic checked by running the backend code; UI / API / database flow NOT tested. | O126: Claude (auto) | P126: 2026-10-21
A127: ATT-019 | B127: Attendance | C127: Processor | D127: Day shift auto-closes at shift end | E127: Positive | F127: P1 | G127: System | H127: Attendance processor enabled | I127: 1. Run processor after shift end | J127: - | K127: Open days are closed at the scheduled close time. | L127: backend src/services/attendance/attendanceProcessor.test.ts | M127: Not Run
A128: ATT-020 | B128: Attendance | C128: Processor | D128: Grace period delays closing | E128: Edge | F128: P2 | G128: System | H128: Grace period configured (e.g. 30 min) | I128: 1. Run processor just after shift end | J128: grace=30 | K128: Day closes only after shift end + grace. | L128: backend src/services/attendance/attendanceProcessor.test.ts | M128: Not Run
A129: ATT-021 | B129: Attendance | C129: Processor | D129: Overnight shift closes next morning | E129: Edge | F129: P2 | G129: System | H129: Night shift | I129: 1. Run processor at night | J129: - | K129: Close time falls on the next calendar day. | L129: backend src/services/attendance/attendanceProcessor.test.ts | M129: Not Run
A130: ATT-022 | B130: Attendance | C130: Processor | D130: Completed run is not re-processed | E130: Edge | F130: P3 | G130: System | H130: Run already complete | I130: 1. Trigger processor again | J130: - | K130: Run is detected as complete and skipped. | L130: backend src/services/attendance/attendanceProcessor.test.ts | M130: Not Run
A131: ATT-023 | B131: Attendance | C131: Regularization | D131: Employee submits regularization | E131: Positive | F131: P0 | G131: Employee | H131: Missing punch-out yesterday | I131: 1. My Attendance > yesterday > Regularize 2. Choose correction type 3. Enter times and reason 4. Submit | J131: punch-out 18:30; reason 'Forgot' | K131: Request created in Pending; goes to approver per workflow. | L131: backend src/services/attendance/attendanceRegularization.test.ts | M131: Not Run
A132: ATT-024 | B132: Attendance | C132: Regularization | D132: Correction type is required | E132: Validation | F132: P1 | G132: Employee | H132: - | I132: 1. Submit regularization without correction type | J132: - | K132: Validation error on correctionType; request not created. | L132: backend src/services/attendance/attendanceRegularization.test.ts | M132: Not Run
A133: ATT-025 | B133: Attendance | C133: Regularization | D133: Manager approves regularization | E133: Positive | F133: P1 | G133: Manager | H133: Pending request from a reportee | I133: 1. Open Requests 2. Approve | J133: - | K133: Attendance day is corrected and recalculated. | L133: backend src/services/attendance/attendanceRegularization.test.ts | M133: Not Run
A134: ATT-026 | B134: Attendance | C134: Regularization | D134: Manager rejects regularization | E134: Positive | F134: P2 | G134: Manager | H134: Pending request | I134: 1. Reject with a reason | J134: - | K134: Request Rejected; day unchanged; employee notified. | L134: backend src/services/attendance/attendanceRegularization.test.ts | M134: Not Run
A135: ATT-027 | B135: Attendance | C135: Regularization | D135: Overnight correction keeps correct dates | E135: Edge | F135: P2 | G135: Employee | H135: Night shift | I135: 1. Regularize with punch-out after midnight | J135: - | K135: Punch-out saved on the next calendar date. | L135: backend src/services/attendance/attendanceRegularization.test.ts | M135: Not Run
...
